pdok_wms_request/__init__.py
pdok_wms_request/aerial_maps.py
pdok_wms_request/tools.py
pdok_wms_request/transforms.py
tests/__init__.py
tests/test_file_handling.py
tests/test_file_locations.py
tests/test_sample.py
vod/__init__.py
vod/common/__init__.py
vod/common/file_handling.py
vod/configuration/__init__.py
vod/configuration/file_locations.py
vod/evaluation/__init__.py
vod/evaluation/eval_from_original.py
vod/evaluation/evaluate.py
vod/evaluation/evaluation_common.py
vod/evaluation/kitti_official_evaluate.py
vod/evaluation/rotate_iou_cpu.py
vod/frame/__init__.py
vod/frame/data_loader.py
vod/frame/labels.py
vod/frame/transformations.py
vod/visualization/__init__.py
vod/visualization/helpers.py
vod/visualization/settings.py
vod/visualization/vis_2d.py
vod/visualization/vis_3d.py
vod_tudelft-1.0.3.dist-info/METADATA
vod_tudelft-1.0.3.dist-info/WHEEL
vod_tudelft-1.0.3.dist-info/top_level.txt
vod_tudelft-1.0.3.dist-info/RECORD
