Metadata-Version: 2.1
Name: vod-tudelft
Version: 1.0.3
Summary: View of Delft dataset devkit
Author: Balazs Szekeres
Author-email: <b.szekeres@student.tudelft.nl>
Keywords: python,video,ai,lidar,radar,camera
Classifier: Intended Audience :: Developers
Classifier: Programming Language :: Python :: 3
Classifier: Operating System :: Unix
Classifier: Operating System :: MacOS :: MacOS X
Classifier: Operating System :: Microsoft :: Windows
Requires-Dist: numpy
Requires-Dist: matplotlib
Requires-Dist: k3d
